eventhubs/__init__.py
eventhubs/__main__.py
eventhubs/cli.py
eventhubs-0.4.dist-info/LICENSE
eventhubs-0.4.dist-info/METADATA
eventhubs-0.4.dist-info/WHEEL
eventhubs-0.4.dist-info/entry_points.txt
eventhubs-0.4.dist-info/top_level.txt
eventhubs-0.4.dist-info/RECORD
