Metadata-Version: 2.2
Name: eventhubs
Version: 0.4
Summary: CLI tool to send and receive event data from Azure Event Hubs
Home-page: https://github.com/zmoog/eventhubs
Author: Maurizio Branca
License: Apache License, Version 2.0
Project-URL: Issues, https://github.com/zmoog/eventhubs/issues
Project-URL: CI, https://github.com/zmoog/eventhubs/actions
Project-URL: Changelog, https://github.com/zmoog/eventhubs/releases
Requires-Python: >=3.8
License-File: LICENSE
Requires-Dist: click
Requires-Dist: azure-eventhub==5.14.0
Provides-Extra: test
Requires-Dist: pytest; extra == "test"
Dynamic: author
Dynamic: description
Dynamic: description-content-type
Dynamic: home-page
Dynamic: license
Dynamic: project-url
Dynamic: provides-extra
Dynamic: requires-dist
Dynamic: requires-python
Dynamic: summary
